<?xml version="1.0" encoding="utf-8" ?>
<dwsync>
<file name="app.css" server="lpvwebcot01.itap.purdue.edu//var/www/html/root/cot/" local="129793244980000000" remote="130308309120000000" Dst="1" />
<file name="host.css" server="lpvwebcot01.itap.purdue.edu//var/www/html/root/cot/" local="129793244980000000" remote="130308309120000000" Dst="1" />
<file name="richcombo.css" server="lpvwebcot01.itap.purdue.edu//var/www/html/root/cot/" local="129793244980000000" remote="130308309130000000" Dst="1" />
<file name="skin.js" server="lpvwebcot01.itap.purdue.edu//var/www/html/root/cot/" local="129793244980000000" remote="130308309130000000" Dst="1" />
<file name="uipanel.css" server="lpvwebcot01.itap.purdue.edu//var/www/html/root/cot/" local="129793244980000000" remote="130308309130000000" Dst="1" />
<file name="app.css" server="ldvwebcot01.www.purdue.edu//var/www/html/root/cot/" local="130264247220000000" remote="130264247220000000" Dst="1" />
<file name="host.css" server="ldvwebcot01.www.purdue.edu//var/www/html/root/cot/" local="130264247220000000" remote="130264247220000000" Dst="1" />
<file name="richcombo.css" server="ldvwebcot01.www.purdue.edu//var/www/html/root/cot/" local="130264247250000000" remote="130264247250000000" Dst="1" />
<file name="skin.js" server="ldvwebcot01.www.purdue.edu//var/www/html/root/cot/" local="130264247250000000" remote="130264247250000000" Dst="1" />
<file name="uipanel.css" server="ldvwebcot01.www.purdue.edu//var/www/html/root/cot/" local="130264247250000000" remote="130264247250000000" Dst="1" />
</dwsync>