<?xml version="1.0" encoding="utf-8" ?>
<dwsync>
<file name="webform.admin.inc" server="lpvwebcot01.itap.purdue.edu//var/www/html/root/cot/" local="129875205500000000" remote="130308309800000000" Dst="1" />
<file name="webform.components.inc" server="lpvwebcot01.itap.purdue.edu//var/www/html/root/cot/" local="129875205500000000" remote="130308309800000000" Dst="1" />
<file name="webform.emails.inc" server="lpvwebcot01.itap.purdue.edu//var/www/html/root/cot/" local="129875205500000000" remote="130308309800000000" Dst="1" />
<file name="webform.export.inc" server="lpvwebcot01.itap.purdue.edu//var/www/html/root/cot/" local="129875205500000000" remote="130308309800000000" Dst="1" />
<file name="webform.options.inc" server="lpvwebcot01.itap.purdue.edu//var/www/html/root/cot/" local="129875205500000000" remote="130308309800000000" Dst="1" />
<file name="webform.pages.inc" server="lpvwebcot01.itap.purdue.edu//var/www/html/root/cot/" local="129875205500000000" remote="130308309800000000" Dst="1" />
<file name="webform.report.inc" server="lpvwebcot01.itap.purdue.edu//var/www/html/root/cot/" local="129875205500000000" remote="130308309800000000" Dst="1" />
<file name="webform.submissions.inc" server="lpvwebcot01.itap.purdue.edu//var/www/html/root/cot/" local="129875205500000000" remote="130308309800000000" Dst="1" />
<file name="webform.admin.inc" server="ldvwebcot01.www.purdue.edu//var/www/html/root/cot/" local="130264249510000000" remote="130264249510000000" Dst="1" />
<file name="webform.components.inc" server="ldvwebcot01.www.purdue.edu//var/www/html/root/cot/" local="130264249510000000" remote="130264249510000000" Dst="1" />
<file name="webform.emails.inc" server="ldvwebcot01.www.purdue.edu//var/www/html/root/cot/" local="130264249510000000" remote="130264249510000000" Dst="1" />
<file name="webform.export.inc" server="ldvwebcot01.www.purdue.edu//var/www/html/root/cot/" local="130264249510000000" remote="130264249510000000" Dst="1" />
<file name="webform.options.inc" server="ldvwebcot01.www.purdue.edu//var/www/html/root/cot/" local="130264249510000000" remote="130264249510000000" Dst="1" />
<file name="webform.pages.inc" server="ldvwebcot01.www.purdue.edu//var/www/html/root/cot/" local="130264249510000000" remote="130264249510000000" Dst="1" />
<file name="webform.report.inc" server="ldvwebcot01.www.purdue.edu//var/www/html/root/cot/" local="130264249510000000" remote="130264249510000000" Dst="1" />
<file name="webform.submissions.inc" server="ldvwebcot01.www.purdue.edu//var/www/html/root/cot/" local="130264249520000000" remote="130264249520000000" Dst="1" />
</dwsync>