<?xml version="1.0" encoding="utf-8" ?>
<dwsync>
<file name="blog.page_title.inc" server="ldvwebcot01.www.purdue.edu//var/www/html/root/cot/" local="130264248570000000" remote="130264248570000000" Dst="1" />
<file name="comment.page_title.inc" server="ldvwebcot01.www.purdue.edu//var/www/html/root/cot/" local="130264248580000000" remote="130264248580000000" Dst="1" />
<file name="forum.page_title.inc" server="ldvwebcot01.www.purdue.edu//var/www/html/root/cot/" local="130264248580000000" remote="130264248580000000" Dst="1" />
<file name="node.page_title.inc" server="ldvwebcot01.www.purdue.edu//var/www/html/root/cot/" local="130264248580000000" remote="130264248580000000" Dst="1" />
<file name="page_title.page_title.inc" server="ldvwebcot01.www.purdue.edu//var/www/html/root/cot/" local="130264248580000000" remote="130264248580000000" Dst="1" />
<file name="taxonomy.page_title.inc" server="ldvwebcot01.www.purdue.edu//var/www/html/root/cot/" local="130264248580000000" remote="130264248580000000" Dst="1" />
<file name="uc_catalog.page_title.inc" server="ldvwebcot01.www.purdue.edu//var/www/html/root/cot/" local="130264248580000000" remote="130264248580000000" Dst="1" />
<file name="user.page_title.inc" server="ldvwebcot01.www.purdue.edu//var/www/html/root/cot/" local="130264248580000000" remote="130264248580000000" Dst="1" />
<file name="views.page_title.inc" server="ldvwebcot01.www.purdue.edu//var/www/html/root/cot/" local="130264248580000000" remote="130264248580000000" Dst="1" />
</dwsync>