<?xml version="1.0" encoding="utf-8" ?>
<dwsync>
<file name="ckffolder.gif" server="lpvwebcot01.itap.purdue.edu//var/www/html/root/cot/" local="129793244980000000" remote="130308309120000000" Dst="1" />
<file name="ckffolderopened.gif" server="lpvwebcot01.itap.purdue.edu//var/www/html/root/cot/" local="129793244980000000" remote="130308309120000000" Dst="1" />
<file name="ckfminus.gif" server="lpvwebcot01.itap.purdue.edu//var/www/html/root/cot/" local="129793244980000000" remote="130308309120000000" Dst="1" />
<file name="ckfnothumb.gif" server="lpvwebcot01.itap.purdue.edu//var/www/html/root/cot/" local="129793244980000000" remote="130308309120000000" Dst="1" />
<file name="ckfplus.gif" server="lpvwebcot01.itap.purdue.edu//var/www/html/root/cot/" local="129793244980000000" remote="130308309120000000" Dst="1" />
<file name="dialog_sides.gif" server="lpvwebcot01.itap.purdue.edu//var/www/html/root/cot/" local="129793244980000000" remote="130308309120000000" Dst="1" />
<file name="dialog_sides.png" server="lpvwebcot01.itap.purdue.edu//var/www/html/root/cot/" local="129793244980000000" remote="130308309120000000" Dst="1" />
<file name="dialog_sides_rtl.png" server="lpvwebcot01.itap.purdue.edu//var/www/html/root/cot/" local="129793244980000000" remote="130308309120000000" Dst="1" />
<file name="icons.png" server="lpvwebcot01.itap.purdue.edu//var/www/html/root/cot/" local="129793244980000000" remote="130308309130000000" Dst="1" />
<file name="spacer.gif" server="lpvwebcot01.itap.purdue.edu//var/www/html/root/cot/" local="129793244980000000" remote="130308309130000000" Dst="1" />
<file name="sprites.png" server="lpvwebcot01.itap.purdue.edu//var/www/html/root/cot/" local="129793244980000000" remote="130308309130000000" Dst="1" />
<file name="sprites_ie6.png" server="lpvwebcot01.itap.purdue.edu//var/www/html/root/cot/" local="129793244980000000" remote="130308309130000000" Dst="1" />
<file name="toolbar_start.gif" server="lpvwebcot01.itap.purdue.edu//var/www/html/root/cot/" local="129793244980000000" remote="130308309130000000" Dst="1" />
<file name="ckffolder.gif" server="ldvwebcot01.www.purdue.edu//var/www/html/root/cot/" local="130264247220000000" remote="130264247220000000" Dst="1" />
<file name="ckffolderopened.gif" server="ldvwebcot01.www.purdue.edu//var/www/html/root/cot/" local="130264247220000000" remote="130264247220000000" Dst="1" />
<file name="ckfminus.gif" server="ldvwebcot01.www.purdue.edu//var/www/html/root/cot/" local="130264247220000000" remote="130264247220000000" Dst="1" />
<file name="ckfnothumb.gif" server="ldvwebcot01.www.purdue.edu//var/www/html/root/cot/" local="130264247220000000" remote="130264247220000000" Dst="1" />
<file name="ckfplus.gif" server="ldvwebcot01.www.purdue.edu//var/www/html/root/cot/" local="130264247220000000" remote="130264247220000000" Dst="1" />
<file name="dialog_sides.gif" server="ldvwebcot01.www.purdue.edu//var/www/html/root/cot/" local="130264247220000000" remote="130264247220000000" Dst="1" />
<file name="dialog_sides.png" server="ldvwebcot01.www.purdue.edu//var/www/html/root/cot/" local="130264247220000000" remote="130264247220000000" Dst="1" />
<file name="dialog_sides_rtl.png" server="ldvwebcot01.www.purdue.edu//var/www/html/root/cot/" local="130264247220000000" remote="130264247220000000" Dst="1" />
<file name="icons.png" server="ldvwebcot01.www.purdue.edu//var/www/html/root/cot/" local="130264247230000000" remote="130264247230000000" Dst="1" />
<file name="spacer.gif" server="ldvwebcot01.www.purdue.edu//var/www/html/root/cot/" local="130264247240000000" remote="130264247240000000" Dst="1" />
<file name="sprites.png" server="ldvwebcot01.www.purdue.edu//var/www/html/root/cot/" local="130264247240000000" remote="130264247240000000" Dst="1" />
<file name="sprites_ie6.png" server="ldvwebcot01.www.purdue.edu//var/www/html/root/cot/" local="130264247240000000" remote="130264247240000000" Dst="1" />
<file name="toolbar_start.gif" server="ldvwebcot01.www.purdue.edu//var/www/html/root/cot/" local="130264247240000000" remote="130264247240000000" Dst="1" />
</dwsync>